{
  "epochs": 100,
  "batch_size": 4096,
  "num_workers": 4,
  "time_steps": 10,
  "hidden_dim": 500,
  "num_layers": 2,
  "seed": 2026,
  "model": "dynsrm",
  "tau": null,
  "tau_response": 1.5,
  "tau_refractory": 16.0,
  "v_threshold": 1.0,
  "v_reset": 0.0,
  "lr": 0.001,
  "alpha": 6.0,
  "input_gain": 0.8,
  "label_scale": 1.0,
  "run_name": "dynsrm__id007__tr1p5__trefr16__vth1__lr0p001__a6__ig0p8__ls1",
  "run_dir": "./result/fintune/runs/dynsrm__id007__tr1p5__trefr16__vth1__lr0p001__a6__ig0p8__ls1"
}